MLTF/__init__.py
MLTF/calc.py
MLTF/info.py
MLTF/layer.py
MLTF/loss_functions.py
MLTF/models.py
MLTF/normer.py
MLTF/plot.py
MLTF/tools.py
MLTF-0.1.2.dist-info/LICENSE
MLTF-0.1.2.dist-info/METADATA
MLTF-0.1.2.dist-info/WHEEL
MLTF-0.1.2.dist-info/top_level.txt
MLTF-0.1.2.dist-info/RECORD
