Metadata-Version: 2.1
Name: MLTF
Version: 0.1.2
Summary: Toolkit for creating ML models using tensorflow. Designed to short-cut implementation of widely used neuronal networks architectures.
Author-email: Andres Navarro Alsina <a.navarro.alsina@gmail.com>
Project-URL: Homepage, https://github.com/andalenavals/MLTF
Project-URL: Bug Tracker, https://github.com/andalenavals/MLTF/issues
Classifier: Programming Language :: Python :: 3
Classifier: License :: OSI Approved :: MIT License
Classifier: Operating System :: OS Independent
Requires-Python: >=3.6
License-File: LICENSE
Requires-Dist: tensorflow
Requires-Dist: numpy
